userproperty/__init__.py
userproperty/userproperty.py
userproperty-0.1.1.dist-info/METADATA
userproperty-0.1.1.dist-info/WHEEL
userproperty-0.1.1.dist-info/top_level.txt
userproperty-0.1.1.dist-info/RECORD
