Metadata-Version: 2.1
Name: userproperty
Version: 0.1.1
Summary: wrapper class for dictionary
Home-page: UNKNOWN
Author: Yongsoo Hwang
License: UNKNOWN
Platform: UNKNOWN
Requires-Python: >=3
